fibonacci.v
// A circuit that counts in Fibonacci numbers
module fibonacci (
    input clk,
    input reset,
    output reg [3:0] fib // 4 bit fibonacci output
);

    reg [3:0] fib_prev, fib_curr;

    always @(posedge clk or posedge reset) begin
        if (reset) begin
            fib_prev <= 4'b0000; // fib(0) = 0
            fib_curr <= 4'b0001; // fib(1) = 1
            fib <= 4'b0000;      // Output initially 0
        end
        else begin // non-blocking assignments used 
            // therefore, must read the old value and THEN update forward
            fib <= fib_curr; // Output current value
            fib_curr <= (fib_prev + fib_curr) & 4'hF;
            fib_prev <= fib_curr;
        end
    end

endmodule

fibonacci.vcd
$version Generated by VerilatedVcd $end
$timescale 1ps $end
 $scope module TOP $end
  $var wire 1 # clk $end
  $var wire 1 $ reset $end
  $var wire 4 % fib [3:0] $end
  $scope module fibonacci $end
   $var wire 1 # clk $end
   $var wire 1 $ reset $end
   $var wire 4 % fib [3:0] $end
   $var wire 4 & fib_prev [3:0] $end
   $var wire 4 ' fib_curr [3:0] $end
  $upscope $end
 $upscope $end
$enddefinitions $end


#0
0#
1$
b0000 %
b0000 &
b0000 '
#1
1#
b0001 '
#2
0#
#3
1#
#4
0#
0$
#5
1#
b0001 %
b0001 &
#6
0#
#7
1#
b0010 '
#8
0#
#9
1#
b0010 %
b0010 &
b0011 '
#10
0#
#11
1#
b0011 %
b0011 &
b0101 '
#12
0#
#13
1#
b0101 %
b0101 &
b1000 '
#14
0#
#15
1#
b1000 %
b1000 &
b1101 '
#16
0#
#17
1#
b1101 %
b1101 &
b0101 '
#18
0#
#19
1#
b0101 %
b0101 &
b0010 '
#20
0#
#21
1#
b0010 %
b0010 &
b0111 '
#22
0#
#23
1#
b0111 %
b0111 &
b1001 '
#24
0#
#25
1#
b1001 %
b1001 &
b0000 '
#26
0#
#27
1#
b0000 %
b0000 &
b1001 '
#28
0#
#29
1#
b1001 %
b1001 &
#30
0#
#31
1#
b0010 '
#32
0#
#33
1#
b0010 %
b0010 &
b1011 '
#34
0#
#35
1#
b1011 %
b1011 &
b1101 '
#36
0#
#37
1#
b1101 %
b1101 &
b1000 '
#38
0#
#39
1#
b1000 %
b1000 &
b0101 '
